nonebot_plugin_VividusFakeAI/__init__.py
nonebot_plugin_VividusFakeAI/learn.py
nonebot_plugin_VividusFakeAI/vivFakeAI_handler.py
nonebot_plugin_vividusfakeai-0.0.2.dist-info/LICENSE
nonebot_plugin_vividusfakeai-0.0.2.dist-info/METADATA
nonebot_plugin_vividusfakeai-0.0.2.dist-info/WHEEL
nonebot_plugin_vividusfakeai-0.0.2.dist-info/RECORD
