Metadata-Version: 2.3
Name: nonebot-plugin-vividusfakeai
Version: 0.0.2
Summary: 模仿群友的聊天!
License: AGPL-3.0
Author: hlfzsi
Requires-Python: >=3.10
Classifier: License :: OSI Approved :: GNU Affero General Public License v3
Classifier: Programming Language :: Python :: 3
Classifier: Programming Language :: Python :: 3.10
Classifier: Programming Language :: Python :: 3.11
Classifier: Programming Language :: Python :: 3.12
Classifier: Programming Language :: Python :: 3.13
Requires-Dist: datasketch (>=1.6.5)
Requires-Dist: jieba (>=0.42.1)
Requires-Dist: nonebot-plugin-localstore (>=0.7.3)
Requires-Dist: nonebot-plugin-vividuscore (>=0.0.1)
